django_jsonlistedit/__init__.py
django_jsonlistedit/static/jsonlistedit/jsonlistedit.css
django_jsonlistedit/static/jsonlistedit/jsonlistedit.js
django_jsonlistedit/templates/jsonlisteditwidget.html
django_jsonlistedit-0.0.8.dist-info/DESCRIPTION.rst
django_jsonlistedit-0.0.8.dist-info/METADATA
django_jsonlistedit-0.0.8.dist-info/RECORD
django_jsonlistedit-0.0.8.dist-info/WHEEL
django_jsonlistedit-0.0.8.dist-info/metadata.json
django_jsonlistedit-0.0.8.dist-info/top_level.txt
