Metadata-Version: 2.0
Name: django-jsonlistedit
Version: 0.0.8
Summary: Core field type and setup for using jsonlistedit to store JSON lists in a text field in django
Home-page: https://github.com/danthedeckie/django_jsonlistedit/
Author: Daniel Fairhead
Author-email: danthedeckie@gmail.com
License: MIT
Platform: UNKNOWN
Classifier: Environment :: Web Environment
Classifier: Intended Audience :: Developers
Classifier: Operating System :: OS Independent
Classifier: Programming Language :: Python
Classifier: Programming Language :: Python :: 3.5
Classifier: Programming Language :: Python :: 3.6
Classifier: Framework :: Django
Requires-Python: >=3.4
Requires-Dist: django (>=1.11.0)
